{
  "dataList": [
    {
      "id": 0,
      "place": "Захваченная Лаборатория Корп. К",
      "model": "그레고르",
      "content": "Это… безусловно, удобно. Кости срастаются за считанные секунды."
    },
    {
      "id": 1,
      "model": "동랑",
      "teller": "Донран",
      "title": "Деп. Развития Продовольств. Ресурсов Корп. К",
      "content": "Корпорация K предоставила нам астрономическую сумму грантов на исследования с целью улучшения этой ампулы. Пожалуйста, не говорите об этом Шренн; она будет дуться на меня месяца три, не меньше."
    },
    {
      "id": 2,
      "model": "료슈",
      "content": "Хмпф… Всё равно этот \"Цикл\" заводит только после нашей смерти, боясь сделать нам больно."
    },
    {
      "id": 3,
      "model": "단테",
      "content": "<……>"
    },
    {
      "id": 4,
      "model": "로쟈",
      "content": "Кажется, я сломала кость в правой руке~ Можно мне ампулу? Мне как-то сложно держать топор."
    },
    {
      "id": 5,
      "content": "Родя встала перед дроном корпорации K и протянула ему правую руку."
    },
    {
      "id": 6,
      "model": "K사앰플기계",
      "teller": "Дрон с Ампулами",
      "title": "Корп. К",
      "content": "Добро пожаловать. Дроны корпорации K всегда к вашим услугам. Ввожу регенерационную ампулу…"
    },
    {
      "id": 7,
      "model": "K사앰플기계",
      "teller": "Дрон с Ампулами",
      "title": "Корп. К",
      "content": "…Невозможно ввести."
    },
    {
      "id": 8,
      "model": "K사앰플기계",
      "teller": "Дрон с Ампулами",
      "title": "Корп. К",
      "content": "Приятельницы типа 3J-54 могут использовать сыворотку, однако регенерационные ампулы можно использовать только на пациентах с потерей крови от 1Lr и больше. Также, так как вы не прошли тест на совместимость с ампулами, мы не несём ответственность за возможные побочные эффекты. Благодарю."
    },
    {
      "id": 9,
      "model": "로쟈",
      "content": "Че~? Вы хотите, чтобы я отрубила себе руку или ногу?"
    },
    {
      "id": 10,
      "model": "싱클레어",
      "content": "Они…"
    },
    {
      "id": 11,
      "model": "싱클레어",
      "content": "Они уже это делают. Смотри на сотрудников корпорации К…"
    },
    {
      "id": 12,
      "model": "싱클레어",
      "content": "Они отрезают себе конечности… чтобы получить ампулу…"
    },
    {
      "id": 13,
      "model": "삼조",
      "teller": "Самджо",
      "title": "Деп. Развития Продовольств. Ресурсов Корп. К",
      "content": "Это необходимое требование. Будет колоссальной финансовой потерей, если использовать регенерационные ампулы на каждую царапину."
    },
    {
      "id": 14,
      "model": "삼조",
      "teller": "Самджо",
      "title": "Деп. Развития Продовольств. Ресурсов Корп. К",
      "content": "Не хочу проводить сравнений, но ценность его куда выше, чем у маленьких фирм вроде вашей."
    },
    {
      "id": 15,
      "model": "싱클레어",
      "content": "……"
    },
    {
      "id": 16,
      "model": "단테",
      "content": "<М-да…>"
    },
    {
      "id": 17,
      "model": "단테",
      "content": "<Похоже, это место опасно. Эти машины слишком грубые… Я могу умереть, если не буду осторожен.>"
    },
    {
      "id": 18,
      "model": "단테",
      "content": "<Похоже, лучше держаться подальше от этого места…>"
    },
    {
      "id": 19,
      "content": "В этот момент что-то пронеслось у меня над головой… То есть, над моей головой с угрожающим свистом."
    },
    {
      "id": 20,
      "model": "단테",
      "content": "<А-а…>"
    },
    {
      "id": 21,
      "model": "이스마엘",
      "content": "Угх…"
    },
    {
      "id": 22,
      "content": "В тот момент, как в мою сторону летел ещё один снаряд, Измаил вытянула руку и приняла удар на себя."
    },
    {
      "id": 23,
      "content": "Повернувшись туда, откуда летели снаряды, я не увидел вражеских роботов."
    },
    {
      "id": 24,
      "content": "Вместо них был дрон корпорации К, сверкающий красным."
    },
    {
      "id": 25,
      "model": "오티스",
      "content": "Менеджер! Вы в порядке?"
    },
    {
      "id": 26,
      "model": "이스마엘",
      "content": "Я приняла удар на себя…"
    },
    {
      "id": 27,
      "model": "오티스",
      "content": "Я должна была принять удар на себя. Чёрт!"
    },
    {
      "id": 28,
      "model": "이스마엘",
      "content": "Простите…"
    },
    {
      "id": 29,
      "model": "오티스",
      "content": "Ха, вот и всё, что могут ваши дорогие роботы. Они стреляют по своим!"
    },
    {
      "id": 30,
      "model": "삼조",
      "teller": "Самджо",
      "title": "Деп. Развития Продовольств. Ресурсов Корп. К",
      "content": "Я вынужден возразить. Это не был дружественный огонь."
    },
    {
      "id": 31,
      "content": "Кричал Самджо, поднимая руку вверх."
    },
    {
      "id": 32,
      "model": "삼조",
      "teller": "Самджо",
      "title": "Деп. Развития Продовольств. Ресурсов Корп. К",
      "content": "Однако… Похоже, что мы не учли все исключения. Прошу прощения за этот недочёт."
    },
    {
      "id": 33,
      "model": "오티스",
      "content": "Что за чушь ты…"
    },
    {
      "id": 34,
      "model": "삼조",
      "teller": "Самджо",
      "title": "Деп. Развития Продовольств. Ресурсов Корп. К",
      "content": "Как вы знаете, вы оказались здесь лишь благодаря капризу мистера Донранга."
    },
    {
      "id": 35,
      "model": "삼조",
      "teller": "Самджо",
      "title": "Деп. Развития Продовольств. Ресурсов Корп. К",
      "content": "Визиты в это место — крайне редкое явление, и были не учтены в планах."
    },
    {
      "id": 36,
      "model": "이스마엘",
      "content": "Что за… Угх… Что ты имеешь в виду?"
    },
    {
      "id": 37,
      "model": "삼조",
      "teller": "Самджо",
      "title": "Деп. Развития Продовольств. Ресурсов Корп. К",
      "content": "Регенераторы корпорации K могут не только лечить."
    },
    {
      "id": 38,
      "model": "이스마엘",
      "content": "Почему… почему моё тело будто тает? Может ли кто-нибудь… объяснить мне…"
    },
    {
      "id": 39,
      "model": "단테",
      "content": "<Измаил!>"
    },
    {
      "id": 40,
      "model": "삼조",
      "teller": "Самджо",
      "title": "Деп. Развития Продовольств. Ресурсов Корп. К",
      "content": "Обычно, дроны корпорации K вводят ампулы регенерации раненым сотрудникам…"
    },
    {
      "id": 41,
      "model": "삼조",
      "teller": "Самджо",
      "title": "Деп. Развития Продовольств. Ресурсов Корп. К",
      "content": "Но дезертирам вводят ампулы разложения."
    },
    {
      "id": 42,
      "model": "단테",
      "content": "<…Потому что я пытался покинуть поле боя?>"
    },
    {
      "id": 43,
      "model": "그레고르",
      "content": "Как же это гнусно… Можно ли устраивать казни без суда в мирное время?"
    },
    {
      "id": 44,
      "model": "그레고르",
      "content": "Ага, почему бы просто не заставить дронов сражаться?"
    },
    {
      "id": 45,
      "model": "삼조",
      "teller": "Самджо",
      "title": "Деп. Развития Продовольств. Ресурсов Корп. К",
      "content": "Гнездо, откуда ты родом, должно быть, ценит человеческую жизнь, верно?"
    },
    {
      "id": 46,
      "model": "삼조",
      "teller": "Самджо",
      "title": "Деп. Развития Продовольств. Ресурсов Корп. К",
      "content": "Стоимость каждого нашего дрона превышает стоимость десяти сотрудников второго класса вместе взятых. Понимаешь?"
    },
    {
      "id": 47,
      "model": "그레고르",
      "content": "\"Ты понимаешь\"… \"ты принимаешь\"…"
    },
    {
      "id": 48,
      "model": "그레고르",
      "content": "Мне слишком часто приходилось сталкиваться с таким дерьмовым принуждением, так что я больше не буду его терпеть."
    },
    {
      "id": 49,
      "model": "파우스트",
      "content": "Я понимаю, откуда это исходит. Исследования показали, что использование дронов корпорации K в симуляциях боя увеличивало шанс победы на 23,5%."
    },
    {
      "id": 50,
      "model": "파우스트",
      "content": "Среди учёных это была довольно известная работа."
    },
    {
      "id": 51,
      "model": "오티스",
      "content": "Ещё с древних времён дезертиры, пытавшиеся сбежать с поля боя, считались более сильным ударом по морали, нежели угроза сокрушительного подавления или слабость лидера."
    },
    {
      "id": 52,
      "model": "오티스",
      "content": "Публичные наказания дезертиров — исторически доказанная тактика, подкреплённая множеством примеров."
    },
    {
      "id": 53,
      "model": "그레고르",
      "content": "Тц. Ну давайте, понимайте."
    },
    {
      "id": 54,
      "model": "단테",
      "content": "<Погодите, о чём вы говорите?>"
    },
    {
      "id": 55,
      "model": "단테",
      "content": "<Посмотрите на Измаил… Она… тает…!>"
    },
    {
      "id": 56,
      "model": "오티스",
      "content": "Ах, прошу прощения за мою небрежность, господин Менеджер."
    },
    {
      "id": 57,
      "model": "오티스",
      "content": "Я не учла, что вам приходится переживать, когда вы обращаете время вспять."
    },
    {
      "id": 58,
      "model": "단테",
      "content": "<Нет, я не…>"
    },
    {
      "id": 59,
      "model": "파우스트",
      "content": "Если это вас беспокоит, стоит поторопиться. В текущем состоянии её сердце должно оставаться невредимым."
    },
    {
      "id": 60,
      "model": "이스마엘",
      "content": "Менеджер… Что… со мной…"
    },
    {
      "id": 61,
      "content": "……"
    },
    {
      "id": 62,
      "content": "Стрелки часов с болью завертелись."
    },
    {
      "id": 63,
      "content": "Тем временем, И Сан смотрел на пустые ампулы, лежащие на полу."
    },
    {
      "id": 64,
      "model": "이상",
      "content": "……"
    }
  ]
}